compositionspace/__init__.py
compositionspace/autophase.py
compositionspace/clustering.py
compositionspace/debugging.py
compositionspace/geometryutils.py
compositionspace/get_file_checksum.py
compositionspace/get_gitrepo_commit.py
compositionspace/get_nexus_version.py
compositionspace/io.py
compositionspace/meshing.py
compositionspace/preparation.py
compositionspace/segmentation.py
compositionspace/utils.py
compositionspace/visualization.py
compositionspace-0.1.4.dist-info/LICENSE
compositionspace-0.1.4.dist-info/METADATA
compositionspace-0.1.4.dist-info/WHEEL
compositionspace-0.1.4.dist-info/top_level.txt
compositionspace-0.1.4.dist-info/RECORD
