Metadata-Version: 2.2
Name: compositionspace
Version: 0.1.4
Summary: APT analysis tools
Author: Alaukik Saxena, Sarath Menon, Mariano Forti, Markus Kühbach
License: BSD 3-Clause License
Project-URL: Homepage, https://github.com/eisenforschung/CompositionSpace
Classifier: Programming Language :: Python :: 3.7
Classifier: Programming Language :: Python :: 3.8
Classifier: Programming Language :: Python :: 3.9
Classifier: Programming Language :: Python :: 3.10
Classifier: Programming Language :: Python :: 3.11
Classifier: Programming Language :: Python :: 3.12
Classifier: Operating System :: OS Independent
Requires-Python: >=3.7
License-File: LICENSE
Requires-Dist: numpy
Requires-Dist: h5py
Requires-Dist: scikit-learn
Requires-Dist: trimesh
Requires-Dist: ifes_apt_tc_data_modeling>=0.2.1
Requires-Dist: pyyaml
Requires-Dist: flatdict
Requires-Dist: lxml
Requires-Dist: jupyter
Requires-Dist: jupyterlab
Requires-Dist: jupyterlab_h5web
Provides-Extra: dev
Requires-Dist: mypy; extra == "dev"
Requires-Dist: ruff; extra == "dev"
Requires-Dist: pandas; extra == "dev"
Requires-Dist: matplotlib; extra == "dev"
Requires-Dist: tqdm; extra == "dev"
Requires-Dist: pyevtk; extra == "dev"
Requires-Dist: pyvista; extra == "dev"
Requires-Dist: pytest; extra == "dev"
Requires-Dist: pytest-timeout; extra == "dev"
Requires-Dist: pytest-cov; extra == "dev"
Requires-Dist: pip-tools; extra == "dev"
